github_storage_system.py
github_storage_system-0.0.4.dist-info/METADATA
github_storage_system-0.0.4.dist-info/WHEEL
github_storage_system-0.0.4.dist-info/top_level.txt
github_storage_system-0.0.4.dist-info/RECORD
