Metadata-Version: 2.1
Name: github-storage-system
Version: 0.0.4
Summary: To use github to store files
Author: prasannan-robots
License: UNKNOWN
Platform: UNKNOWN
Classifier: Programming Language :: Python :: 3
Classifier: License :: OSI Approved :: MIT License
Classifier: Operating System :: OS Independent
Requires-Python: >=3.6
Requires-Dist: PyGithub
